{
  "$schema": "http://json-schema.org/draft-04/schema#",
  "id": "/",
  "type": "object",
  "properties": {
    "_id": {
      "id": "_id",
      "type": "string"
    },
    "acronym": {
      "id": "acronym",
      "type": "string"
    },
    "name": {
      "id": "name",
      "type": "string"
    },
    "logo_url": {
      "id": "logo_url",
      "type": "string"
    },
    "license_code": {
      "id": "license_code",
      "type": "string"
    },
    "sponsors": {
      "id": "sponsors",
      "type": "array",
      "items": {
        "id": "auto-generated-schema-620"
      }
    }
  },
  "required": [
    "_id",
    "acronym",
    "name",
    "logo_url",
    "license_code",
    "sponsors"
  ]
}
